gocardless_connector/__init__.py
gocardless_connector/connector.py
tests/__init__.py
gocardless_fintools-0.5.dist-info/LICENSE
gocardless_fintools-0.5.dist-info/METADATA
gocardless_fintools-0.5.dist-info/WHEEL
gocardless_fintools-0.5.dist-info/entry_points.txt
gocardless_fintools-0.5.dist-info/top_level.txt
gocardless_fintools-0.5.dist-info/RECORD
