Metadata-Version: 2.2
Name: gocardless-fintools
Version: 0.5
Summary: A CLI tool for managing bank account connections via GoCardless Bank Account Data API
Home-page: https://github.com/thetombrider/gocardlessconnection
Author: thetombrider
Author-email: tommasominuto@gmail.com
Project-URL: Bug Tracker, https://github.com/thetombrider/gocardlessconnection/issues
Project-URL: Documentation, https://github.com/thetombrider/gocardlessconnection#readme
Project-URL: Source Code, https://github.com/thetombrider/gocardlessconnection
Classifier: Programming Language :: Python :: 3
Classifier: License :: OSI Approved :: MIT License
Classifier: Operating System :: OS Independent
Classifier: Development Status :: 4 - Beta
Classifier: Environment :: Console
Classifier: Intended Audience :: Financial and Insurance Industry
Classifier: Topic :: Office/Business :: Financial
Requires-Python: >=3.6
License-File: LICENSE
Requires-Dist: python-dotenv
Requires-Dist: nordigen-python
Requires-Dist: click
Requires-Dist: pandas
Dynamic: author
Dynamic: author-email
Dynamic: classifier
Dynamic: description
Dynamic: description-content-type
Dynamic: home-page
Dynamic: project-url
Dynamic: requires-dist
Dynamic: requires-python
Dynamic: summary
